{
    "APP_NAME": "Make Art",
    "APP_DESCRIPTION": "Make Art with code",
    "ICONS": {
        "UWP": "icon/kano-draw-windows.png",
        "FAVICON": "icon/kano-draw-windows.png"
    },
    "UWP": {
        "PACKAGE_NAME": "KanoComputing.MakeArt",
        "PACKAGE_DISPLAY_NAME": "Make Art",
        "PUBLISHER": "CN=5F3CCEA7-D562-4AF0-A330-11A092BC3806",
        "PUBLISHER_DISPLAY_NAME": "Kano Computing",
        "EXTENSIONS": [{
            "TYPE": "FILE_TYPE_ASSOCIATION",
            "NAME": "make-art",
            "LOGO": "assets/kano-draw-windows.png",
            "DISPLAY_NAME": "Make Art",
            "SUPPORTED_FILE_TYPES": [{
                "CONTENT_TYPE": "text/draw",
                "FILE_TYPE": ".draw"
            }]
        }]
    },
    "BACKGROUND_COLOR": "#51555c",
    "CONFIG": {
        "DEBUG_LEVEL"     : 1,
        "PRODUCTION"      : false,
        "OFFLINE"         : false,
        "API_URL"         : false,
        "API_URL_V2": "https://worldapi.kes.kano.me",
        "WORLD_URL"       : false,
        "CHALLENGES_URL": "assets/challenges/descriptors",
        "DOMAIN_CFG": {
            "hourofcode.kano.me": {
                "mapToWorld": "pixelhack",
                "hideShares": true
            },
            "csedweek.kano.me": {
                "mapToWorld": "pixelhack",
                "hideShares": true
            }
        },
        "DEFAULT_AVATAR"  : "https://s3-eu-west-1.amazonaws.com/world.kano.me/users/avatars/563890fec4d6960800c721f7/avatar-circle.png",
        "languageSynonyms": {
            "color": ["colour"],
            "grey": ["gray"]
        }
    },
    "SHARING_URL": "https://staging.sharing.kano.me",
    "TELEMETRY_URL": "https://telemetry.kessandbox.co.uk/batch"
}